[
  {
    "candidate_name": "GAYNOR, MICHAEL GREGORY WILLIAM MR SR.",
    "candidate_id": "H6KS04199",
    "committee_id": "C00891119",
    "individual_contributions": [],
    "pac_contributions": []
  },
  {
    "candidate_name": "INGRAM, DENARD",
    "candidate_id": "H4CA12162",
    "committee_id": "C00770271",
    "individual_contributions": [],
    "pac_contributions": []
  },
  {
    "candidate_name": "GAYNOR, MICHAEL GREGORY WILLIAM MR SR.",
    "candidate_id": "H8KS01050",
    "committee_id": null,
    "individual_contributions": [],
    "pac_contributions": []
  },
  {
    "candidate_name": "INGRAM, JAMES RONALD",
    "candidate_id": "H6MO06252",
    "committee_id": null,
    "individual_contributions": [],
    "pac_contributions": []
  },
  {
    "candidate_name": "AARON, RICHARD",
    "candidate_id": "H6MI04188",
    "committee_id": "C00898031",
    "individual_contributions": [],
    "pac_contributions": []
  },
  {
    "candidate_name": "BURTON, DANIEL LEROY JR",
    "candidate_id": "H2PA00034",
    "committee_id": "C00776286",
    "individual_contributions": [],
    "pac_contributions": []
  },
  {
    "candidate_name": "BURTON, DANNY L",
    "candidate_id": "H2IN06023",
    "committee_id": "C00145862",
    "individual_contributions": [],
    "pac_contributions": []
  },
  {
    "candidate_name": "AASEN, ANDREW J",
    "candidate_id": "H4OR05312",
    "committee_id": "C00846311",
    "individual_contributions": [],
    "pac_contributions": []
  },
  {
    "candidate_name": "BURTON, HASANI",
    "candidate_id": "H0TX30099",
    "committee_id": "C00726067",
    "individual_contributions": [],
    "pac_contributions": []
  },
  {
    "candidate_name": "ABBITT, DAVE",
    "candidate_id": "H4CA32152",
    "committee_id": "C00859025",
    "individual_contributions": [],
    "pac_contributions": []
  },
  {
    "candidate_name": "ABDELHAMID, RANA",
    "candidate_id": "H2NY12197",
    "committee_id": "C00776658",
    "individual_contributions": [],
    "pac_contributions": [
      {
        "name": "ADP",
        "amount": 802.99,
        "date": "2025-02-20",
        "city": "ROSELAND",
        "state": "NJ",
        "employer": null,
        "occupation": null,
        "committee_id": "C00776658"
      },
      {
        "name": "LANDER 2025",
        "amount": 1850.0,
        "date": "2025-01-14",
        "city": "NEW YORK",
        "state": "NY",
        "employer": null,
        "occupation": null,
        "committee_id": "C00776658"
      }
    ]
  },
  {
    "candidate_name": "BURTON, PAUL",
    "candidate_id": "H4AZ01236",
    "committee_id": "C00931477",
    "individual_contributions": [],
    "pac_contributions": []
  },
  {
    "candidate_name": "ABDULLE, ABDI",
    "candidate_id": "H6MN02289",
    "committee_id": null,
    "individual_contributions": [],
    "pac_contributions": []
  },
  {
    "candidate_name": "BURT, STEVEN",
    "candidate_id": "H6UT04024",
    "committee_id": "C00922898",
    "individual_contributions": [
      {
        "name": "BURT, BECKY",
        "amount": 500.0,
        "date": "2025-12-31",
        "city": "SOUTH JORDAN",
        "state": "UT",
        "employer": "UNIVERSITY OF UTAH HEALTH",
        "occupation": "DNP"
      },
      {
        "name": "KAYE, ANTHONY",
        "amount": 500.0,
        "date": "2025-12-30",
        "city": "SALT LAKE CITY",
        "state": "UT",
        "employer": "RETIRED",
        "occupation": "RETIRED"
      },
      {
        "name": "FREEMAN, JOSH",
        "amount": 3500.0,
        "date": "2025-12-30",
        "city": "SOUTH JORDAN",
        "state": "UT",
        "employer": "FREEMAN LOVELL",
        "occupation": "ATTORNEY"
      },
      {
        "name": "KLINE, ASHLEY",
        "amount": 250.0,
        "date": "2025-12-29",
        "city": "SOUTH JORDAN",
        "state": "UT",
        "employer": "ALTA RIDGE DENTAL",
        "occupation": "DENTAL HYGENIST"
      },
      {
        "name": "BURT, PEGGY",
        "amount": 200.0,
        "date": "2025-12-29",
        "city": "EAGLE MOUNTAIN",
        "state": "UT",
        "employer": "RETIRED",
        "occupation": "RETIRED"
      },
      {
        "name": "NEWMAN, JEREMY",
        "amount": 1000.0,
        "date": "2025-12-27",
        "city": "SOUTH JORDAN",
        "state": "UT",
        "employer": "SPERRY EQUITIES",
        "occupation": "DIRECTOR ASSET MANAGEMENT"
      },
      {
        "name": "HUGHES, ROBERT",
        "amount": 800.0,
        "date": "2025-11-24",
        "city": "SOUTH JORDAN",
        "state": "UT",
        "employer": "PARSONS BEHLE & LATIMER",
        "occupation": "ATTORNEY"
      },
      {
        "name": "TURNER, CHRISTOPHER",
        "amount": 250.0,
        "date": "2025-11-17",
        "city": "EAGLE MOUNTAIN",
        "state": "UT",
        "employer": "RETIRED",
        "occupation": "RETIRED"
      },
      {
        "name": "SCHOW, GREG",
        "amount": 1000.0,
        "date": "2025-11-02",
        "city": "FARMINGTON",
        "state": "UT",
        "employer": "ASPEN MOUNTAIN PARTNERS",
        "occupation": "ENTREPRENEUR"
      },
      {
        "name": "NEILSON, JED",
        "amount": 500.0,
        "date": "2025-11-01",
        "city": "STATE COLLEGE",
        "state": "PA",
        "employer": "PENN STATE UNIVERSITY",
        "occupation": "PROFESSOR"
      },
      {
        "name": "CANTWELL, NICK",
        "amount": 1000.0,
        "date": "2025-10-31",
        "city": "HERRIMAN",
        "state": "UT",
        "employer": "CYPRUS FAMILY DENTAL",
        "occupation": "DENTIST"
      },
      {
        "name": "SHAPER, PETER",
        "amount": 1000.0,
        "date": "2025-10-25",
        "city": "HOUSTON",
        "state": "TX",
        "employer": "POSIGEN SOLAR",
        "occupation": "CEO"
      },
      {
        "name": "BURT, PEGGY",
        "amount": 500.0,
        "date": "2025-10-25",
        "city": "EAGLE MOUNTAIN",
        "state": "UT",
        "employer": "RETIRED",
        "occupation": "RETIRED"
      },
      {
        "name": "HEALEY, BENJAMIN",
        "amount": 324.0,
        "date": "2025-10-22",
        "city": "BROOKLYN",
        "state": "NY",
        "employer": "POSIGEN",
        "occupation": "MANAGER"
      },
      {
        "name": "KENNEDY, DAVID",
        "amount": 1000.0,
        "date": "2025-10-21",
        "city": "LEHI",
        "state": "UT",
        "employer": "AHIP",
        "occupation": "ANALYST"
      }
    ],
    "pac_contributions": [
      {
        "name": "BURT, STEVEN",
        "amount": 3587.0,
        "date": "2025-12-10",
        "city": "SOUTH JORDAN",
        "state": "UT",
        "employer": "CANDIDATE",
        "occupation": "CANDIDATE",
        "committee_id": "C00922898"
      },
      {
        "name": "BURT, STEVEN",
        "amount": 2052.0,
        "date": "2025-12-10",
        "city": "SOUTH JORDAN",
        "state": "UT",
        "employer": "CANDIDATE",
        "occupation": "CANDIDATE",
        "committee_id": "C00922898"
      }
    ]
  },
  {
    "candidate_name": "ABEL, WILLIAM P",
    "candidate_id": "H6TX31136",
    "committee_id": "C00919480",
    "individual_contributions": [],
    "pac_contributions": [
      {
        "name": "ABEL, WILLIAM P",
        "amount": 3125.0,
        "date": "2025-11-28",
        "city": "COPPERAS COVE",
        "state": "TX",
        "employer": "RETIRED ARMY",
        "occupation": "RETIRED ARMY",
        "committee_id": "C00919480"
      },
      {
        "name": "ABEL, WILLIAM P",
        "amount": 155.69,
        "date": "2025-10-27",
        "city": "COPPERAS COVE",
        "state": "TX",
        "employer": "RETIRED ARMY",
        "occupation": "RETIRED ARMY",
        "committee_id": "C00919480"
      },
      {
        "name": "ABEL, WILLIAM P",
        "amount": 414.36,
        "date": "2025-10-27",
        "city": "COPPERAS COVE",
        "state": "TX",
        "employer": "RETIRED ARMY",
        "occupation": "RETIRED ARMY",
        "committee_id": "C00919480"
      },
      {
        "name": "ABEL, WILLIAM P",
        "amount": 699.48,
        "date": "2025-10-24",
        "city": "COPPERAS COVE",
        "state": "TX",
        "employer": "RETIRED ARMY",
        "occupation": "RETIRED ARMY",
        "committee_id": "C00919480"
      },
      {
        "name": "ABEL, WILLIAM P",
        "amount": 111.05,
        "date": "2025-10-07",
        "city": "COPPERAS COVE",
        "state": "TX",
        "employer": "RETIRED ARMY",
        "occupation": "RETIRED ARMY",
        "committee_id": "C00919480"
      },
      {
        "name": "ABEL, WILLIAM P",
        "amount": 189.0,
        "date": "2025-10-06",
        "city": "COPPERAS COVE",
        "state": "TX",
        "employer": "RETIRED ARMY",
        "occupation": "RETIRED ARMY",
        "committee_id": "C00919480"
      },
      {
        "name": "ABEL, WILLIAM P",
        "amount": 1000.0,
        "date": "2025-09-25",
        "city": "COPPERAS COVE",
        "state": "TX",
        "employer": "RETIRED ARMY",
        "occupation": "RETIRED ARMY",
        "committee_id": "C00919480"
      },
      {
        "name": "ABEL, WILLIAM P",
        "amount": 200.0,
        "date": "2025-09-15",
        "city": "COPPERAS COVE",
        "state": "TX",
        "employer": "RETIRED ARMY",
        "occupation": "RETIRED ARMY",
        "committee_id": "C00919480"
      }
    ]
  },
  {
    "candidate_name": "BUSBY, BRADY",
    "candidate_id": "H4AZ20012",
    "committee_id": "C00859322",
    "individual_contributions": [],
    "pac_contributions": []
  },
  {
    "candidate_name": "ABNEY, MARVIN L.",
    "candidate_id": "H4RI01281",
    "committee_id": "C00839126",
    "individual_contributions": [
      {
        "name": "TSANDILAS, MICHAEL J.",
        "amount": 350.0,
        "date": "2025-05-13",
        "city": "NEWPORT",
        "state": "RI",
        "employer": "SUFFOLK CAPITAL",
        "occupation": "COMMERCIAL REAL ESTATE"
      },
      {
        "name": "SARDELLA, RICHARD",
        "amount": 2000.0,
        "date": "2025-05-13",
        "city": "NEWPORT",
        "state": "RI",
        "employer": "RETIRED",
        "occupation": "RETIRED"
      },
      {
        "name": "CEGLIE, LYNN",
        "amount": 800.0,
        "date": "2025-05-13",
        "city": "NEWPORT",
        "state": "RI",
        "employer": "RETIRED",
        "occupation": "RETIRED"
      },
      {
        "name": "BOYLE, CHRISTOPHER",
        "amount": 1500.0,
        "date": "2025-05-11",
        "city": "NEWPORT",
        "state": "RI",
        "employer": "LAW OFFICES OF CHRISTOPHER BOYLE",
        "occupation": "ATTONERY"
      },
      {
        "name": "PAIVA WEED, TERESA",
        "amount": 1750.0,
        "date": "2025-05-09",
        "city": "NEWPORT",
        "state": "RI",
        "employer": "HOSPITAL ASSOCIATION OF RHODE ISLAND",
        "occupation": "PRESIDENT"
      },
      {
        "name": "VAREIKA, WILLIAM",
        "amount": 700.0,
        "date": "2025-05-06",
        "city": "NEWPORT",
        "state": "RI",
        "employer": "RETIRED",
        "occupation": "RETIRED"
      },
      {
        "name": "SHEKARCHI, K. JOSEPH",
        "amount": 1000.0,
        "date": "2025-05-01",
        "city": "WARWICK",
        "state": "RI",
        "employer": "SELF",
        "occupation": "LAWYER"
      },
      {
        "name": "WINTHROP, HENRY",
        "amount": 450.0,
        "date": "2025-04-25",
        "city": "NEWPORT",
        "state": "RI",
        "employer": "RETIRED",
        "occupation": "RETIRED"
      },
      {
        "name": "LEHANE, JAMES",
        "amount": 1200.0,
        "date": "2025-04-25",
        "city": "PORTSMOUTH",
        "state": "RI",
        "employer": "RETIRED",
        "occupation": "RETIRED"
      },
      {
        "name": "JACKSON, J RUSSELL",
        "amount": 450.0,
        "date": "2025-04-25",
        "city": "NEWPORT",
        "state": "RI",
        "employer": "SELF",
        "occupation": "LAWYER"
      },
      {
        "name": "HOCKADAY, TOM",
        "amount": 600.0,
        "date": "2025-04-20",
        "city": "PORTSMOUTH",
        "state": "RI",
        "employer": "SELF EMPLOYED",
        "occupation": "PUBLIC AFFAIRS CONSULTANT"
      },
      {
        "name": "DONAVAN BROOKS, ELIZABETH",
        "amount": 1000.0,
        "date": "2025-02-11",
        "city": "NEWPORT",
        "state": "RI",
        "employer": "RETIRED",
        "occupation": "RETIRED"
      },
      {
        "name": "BROOKS, ALEXANDRA",
        "amount": 1000.0,
        "date": "2025-02-11",
        "city": "NEWPORT",
        "state": "RI",
        "employer": "NONE",
        "occupation": "UNEMPLOYED"
      },
      {
        "name": "SANDMAN, PEGGY",
        "amount": 1500.0,
        "date": "2025-02-09",
        "city": "TIVERTON",
        "state": "RI",
        "employer": "RETIRED",
        "occupation": "RETIRED"
      }
    ],
    "pac_contributions": []
  },
  {
    "candidate_name": "BUSCH, EMILY",
    "candidate_id": "H4MI10107",
    "committee_id": "C00837971",
    "individual_contributions": [],
    "pac_contributions": []
  },
  {
    "candidate_name": "ABOLFAZLI, MARYAM.",
    "candidate_id": "H4TN05145",
    "committee_id": "C00874602",
    "individual_contributions": [],
    "pac_contributions": []
  },
  {
    "candidate_name": "BUSHAW, DAVE",
    "candidate_id": "H6IA02260",
    "committee_id": "C00926360",
    "individual_contributions": [
      {
        "name": "FREDERIKSEN, GERI",
        "amount": 104.0,
        "date": "2025-12-26",
        "city": "COUNCIL BLUFFS",
        "state": "IA",
        "employer": "RETIRED",
        "occupation": "RETIRED"
      },
      {
        "name": "FREDERIKSEN, GERI",
        "amount": 10.63,
        "date": "2025-12-19",
        "city": "COUNCIL BLUFFS",
        "state": "IA",
        "employer": "RETIRED",
        "occupation": "RETIRED"
      },
      {
        "name": "FREDERICKSEN, RACHEL",
        "amount": 259.63,
        "date": "2025-12-16",
        "city": "CEDAR FALLS",
        "state": "IA",
        "employer": "JACK HENRY",
        "occupation": "TECHNICAL ACCOUNT MANAGER"
      },
      {
        "name": "HOPE, DANIEL",
        "amount": 500.0,
        "date": "2025-12-12",
        "city": "WEST UNION",
        "state": "IA",
        "employer": "BOONE'S SNOW REMOVAL",
        "occupation": "OWNER"
      },
      {
        "name": "HUBBARD, RICHARD",
        "amount": 519.0,
        "date": "2025-12-02",
        "city": "HOLLIS",
        "state": "NH",
        "employer": "SELF",
        "occupation": "CONSULTANT"
      },
      {
        "name": "FREDERIKSEN, GERI",
        "amount": 104.0,
        "date": "2025-11-26",
        "city": "COUNCIL BLUFFS",
        "state": "IA",
        "employer": "RETIRED",
        "occupation": "RETIRED"
      },
      {
        "name": "GARDNER, CATHERINE",
        "amount": 259.63,
        "date": "2025-11-22",
        "city": "RALEIGH",
        "state": "NC",
        "employer": "HAWTHORNE",
        "occupation": "LEASING AGENT"
      },
      {
        "name": "PROVENZA, KARLEE",
        "amount": 280.38,
        "date": "2025-11-13",
        "city": "LARAMIE",
        "state": "WY",
        "employer": "WYOMING HOUSE OF REPRESENTATIVES",
        "occupation": "REPRESENTATIVE"
      },
      {
        "name": "MONTELONGO, MATTHEW",
        "amount": 259.63,
        "date": "2025-11-13",
        "city": "NEW YORK",
        "state": "NY",
        "employer": "SELF-EMPLOYED",
        "occupation": "FREELANCE WRITER"
      },
      {
        "name": "MOORMAN, JESS",
        "amount": 207.75,
        "date": "2025-11-12",
        "city": "CEDAR RAPIDS",
        "state": "IA",
        "employer": "COLLINS AEROSPACE",
        "occupation": "QUALITY ASSURANCE"
      },
      {
        "name": "FREDERIKSEN, GERI",
        "amount": 259.63,
        "date": "2025-11-12",
        "city": "COUNCIL BLUFFS",
        "state": "IA",
        "employer": "RETIRED",
        "occupation": "RETIRED"
      }
    ],
    "pac_contributions": [
      {
        "name": "BUSHAW, DAVE",
        "amount": 90.04,
        "date": "2025-12-01",
        "city": "WEST UNION",
        "state": "IA",
        "employer": null,
        "occupation": null,
        "committee_id": "C00926360"
      },
      {
        "name": "BUSHAW, DAVE",
        "amount": 1345.2,
        "date": "2025-11-21",
        "city": "WEST UNION",
        "state": "IA",
        "employer": null,
        "occupation": null,
        "committee_id": "C00926360"
      },
      {
        "name": "BUSHAW, DAVE",
        "amount": 93.03,
        "date": "2025-11-07",
        "city": "WEST UNION",
        "state": "IA",
        "employer": null,
        "occupation": null,
        "committee_id": "C00926360"
      },
      {
        "name": "BUSHAW, DAVE",
        "amount": 330.0,
        "date": "2025-11-01",
        "city": "WEST UNION",
        "state": "IA",
        "employer": null,
        "occupation": null,
        "committee_id": "C00926360"
      }
    ]
  },
  {
    "candidate_name": "ABOUJAOUDE, ROCK ADEL MR. JR",
    "candidate_id": "H4FL02112",
    "committee_id": "C00876888",
    "individual_contributions": [],
    "pac_contributions": []
  },
  {
    "candidate_name": "BUSH, CORI",
    "candidate_id": "H8MO01143",
    "committee_id": "C00922153",
    "individual_contributions": [],
    "pac_contributions": []
  },
  {
    "candidate_name": "ABOUJAOUDE, ROCK ADEL MR. JR.",
    "candidate_id": "H6FL03123",
    "committee_id": "C00923086",
    "individual_contributions": [],
    "pac_contributions": []
  },
  {
    "candidate_name": "BUSKIRK, PAUL",
    "candidate_id": "H4KS01083",
    "committee_id": "C00854216",
    "individual_contributions": [],
    "pac_contributions": []
  },
  {
    "candidate_name": "ABRAHAM, SHELLY JOHN",
    "candidate_id": "H4GA06137",
    "committee_id": "C00844803",
    "individual_contributions": [],
    "pac_contributions": []
  },
  {
    "candidate_name": "BUSSE, RYAN",
    "candidate_id": "H6MT01145",
    "committee_id": "C00933473",
    "individual_contributions": [],
    "pac_contributions": []
  },
  {
    "candidate_name": "ABRAMSON, MAX",
    "candidate_id": "H4NH00013",
    "committee_id": "C00865543",
    "individual_contributions": [],
    "pac_contributions": []
  },
  {
    "candidate_name": "ABRATE, DENIS CHARLES MR.",
    "candidate_id": "H6CO08039",
    "committee_id": "C00903161",
    "individual_contributions": [],
    "pac_contributions": []
  },
  {
    "candidate_name": "ABREVAYA, DAVID",
    "candidate_id": "H6IL09186",
    "committee_id": "C00902346",
    "individual_contributions": [],
    "pac_contributions": []
  },
  {
    "candidate_name": "A BROWN, MICHAEL",
    "candidate_id": "H4DC01033",
    "committee_id": "C00866632",
    "individual_contributions": [],
    "pac_contributions": []
  },
  {
    "candidate_name": "ABU-GHAZALAH, MAAD",
    "candidate_id": "H6NC07204",
    "committee_id": "C00922310",
    "individual_contributions": [
      {
        "name": "COOK, ROGER",
        "amount": 1000.0,
        "date": "2025-12-29",
        "city": "WILMINGTON",
        "state": "NC",
        "employer": "RETIRED",
        "occupation": "LAWYER"
      },
      {
        "name": "DRACH, BOB",
        "amount": 500.0,
        "date": "2025-10-06",
        "city": "WILMINGTON",
        "state": "NC",
        "employer": "SELF",
        "occupation": "ACCOUNTANT"
      }
    ],
    "pac_contributions": [
      {
        "name": "LIBERTARIAN PARTY OF NORTH CAROLINA",
        "amount": 1740.0,
        "date": "2025-12-19",
        "city": "RALEIGH",
        "state": "NC",
        "employer": null,
        "occupation": null,
        "committee_id": "C00922310"
      },
      {
        "name": "ABU-GHAZALAH, MAAD",
        "amount": 53.37,
        "date": "2025-11-20",
        "city": "WILMINGTON",
        "state": "NC",
        "employer": "RETIRED",
        "occupation": "LAWYER",
        "committee_id": "C00922310"
      },
      {
        "name": "ABU-GHAZALAH, MAAD",
        "amount": 86.1,
        "date": "2025-10-06",
        "city": "WILMINGTON",
        "state": "NC",
        "employer": "RETIRED",
        "occupation": "LAWYER",
        "committee_id": "C00922310"
      },
      {
        "name": "ABU-GHAZALAH, MAAD",
        "amount": 10.19,
        "date": "2025-10-06",
        "city": "WILMINGTON",
        "state": "NC",
        "employer": "RETIRED",
        "occupation": "LAWYER",
        "committee_id": "C00922310"
      }
    ]
  },
  {
    "candidate_name": "MOISE, RUDOLPH",
    "candidate_id": "H0FL17118",
    "committee_id": "C00935460",
    "individual_contributions": [],
    "pac_contributions": []
  },
  {
    "candidate_name": "CABLE, CONRAD ROBERTS",
    "candidate_id": "H6LA04187",
    "committee_id": "C00909762",
    "individual_contributions": [
      {
        "name": "RATCLIFF, JOY",
        "amount": 3850.0,
        "date": "2025-09-28",
        "city": "SHREVEPORT",
        "state": "LA",
        "employer": "NOT EMPLOYED",
        "occupation": "NOT EMPLOYED"
      },
      {
        "name": "HAJIAKBARIFINI, JOSHUA",
        "amount": 250.0,
        "date": "2025-09-28",
        "city": "BATON ROUGE",
        "state": "LA",
        "employer": "BANK OF MINGO",
        "occupation": "VICE PRESIDENT"
      },
      {
        "name": "BANKSTON, KEVIN",
        "amount": 250.0,
        "date": "2025-09-28",
        "city": "WASHINGTON",
        "state": "DC",
        "employer": "CENTER FOR DEMOCRACY & TECHNOLOGY",
        "occupation": "POLICY"
      },
      {
        "name": "VOSS, JACKSON",
        "amount": 50.0,
        "date": "2025-09-21",
        "city": "NEW ORLEANS",
        "state": "LA",
        "employer": "ALLIANCE FOR AFFORDABLE ENERGY",
        "occupation": "POLICY COORDINATOR"
      },
      {
        "name": "SPARKS, MARION",
        "amount": 250.0,
        "date": "2025-09-21",
        "city": "LAFAYETTE",
        "state": "LA",
        "employer": "CAPITOLA SURGEY CENTER",
        "occupation": "RN"
      },
      {
        "name": "ARMSTRONG, JOHNNY",
        "amount": 250.0,
        "date": "2025-09-21",
        "city": "RUSTON",
        "state": "LA",
        "employer": "NOT EMPLOYED",
        "occupation": "NOT EMPLOYED"
      },
      {
        "name": "RATCLIFF, JOHN",
        "amount": 3500.0,
        "date": "2025-09-14",
        "city": "SHREVEPORT",
        "state": "LA",
        "employer": "NOT EMPLOYED",
        "occupation": "NOT EMPLOYED"
      },
      {
        "name": "MOORE, ANNE",
        "amount": 500.0,
        "date": "2025-09-14",
        "city": "NEW ORLEANS",
        "state": "LA",
        "employer": "MOONES ENTERPRISES LLC",
        "occupation": "BUSINESS OWNER"
      },
      {
        "name": "WELLS, VERNON",
        "amount": 500.0,
        "date": "2025-09-07",
        "city": "MONROE",
        "state": "LA",
        "employer": "BROADCOM",
        "occupation": "ACCOUNT MANAGER"
      },
      {
        "name": "JONES, PAMELA",
        "amount": 1000.0,
        "date": "2025-09-07",
        "city": "SHREVEPORT",
        "state": "LA",
        "employer": "DOWNER JONES MARINO & WILHITE LLC",
        "occupation": "LAWYER"
      },
      {
        "name": "JACQUEMIN, OLIVIA",
        "amount": 250.0,
        "date": "2025-09-07",
        "city": "VIENNA",
        "state": "VA",
        "employer": "CORE CANINE",
        "occupation": "DOG TRAINER"
      },
      {
        "name": "JACQUEMIN, OLIVIA",
        "amount": 20.0,
        "date": "2025-09-07",
        "city": "VIENNA",
        "state": "VA",
        "employer": "CORE CANINE",
        "occupation": "DOG TRAINER"
      },
      {
        "name": "HALE, KATHERINE",
        "amount": 250.0,
        "date": "2025-09-07",
        "city": "CHICAGO",
        "state": "IL",
        "employer": "LEO BURNETT",
        "occupation": "CREATIVE DIRECTOR"
      },
      {
        "name": "BLELL, DANIEL",
        "amount": 1000.0,
        "date": "2025-09-07",
        "city": "CONROE",
        "state": "TX",
        "employer": "UNITED AIRLINES",
        "occupation": "PILOT"
      },
      {
        "name": "BARNES, KENNETH",
        "amount": 250.0,
        "date": "2025-09-07",
        "city": "NEW ORLEANS",
        "state": "LA",
        "employer": "LAW OFFICE OF KENN BARNES",
        "occupation": "ATTORNEY"
      },
      {
        "name": "RATNER, EMILY",
        "amount": 1000.0,
        "date": "2025-08-31",
        "city": "NEW ORLEANS",
        "state": "LA",
        "employer": "SELF",
        "occupation": "LAWYER"
      },
      {
        "name": "VOSS, JACKSON",
        "amount": 50.0,
        "date": "2025-08-24",
        "city": "NEW ORLEANS",
        "state": "LA",
        "employer": "ALLIANCE FOR AFFORDABLE ENERGY",
        "occupation": "POLICY COORDINATOR"
      },
      {
        "name": "LANDRY, MANDIE",
        "amount": 250.0,
        "date": "2025-08-24",
        "city": "NEW ORLEANS",
        "state": "LA",
        "employer": "SELF",
        "occupation": "LAWYER"
      },
      {
        "name": "CHEEK, LINDSEY",
        "amount": 500.0,
        "date": "2025-08-24",
        "city": "NEW ORLEANS",
        "state": "LA",
        "employer": "THE CHEEK LAW FIRM LLC",
        "occupation": "ATTORNEY/OWNER"
      },
      {
        "name": "LEVY, DAVID",
        "amount": 1000.0,
        "date": "2025-08-17",
        "city": "NEW IBERIA",
        "state": "LA",
        "employer": "PETROTECHNOLOGIES INC",
        "occupation": "BUSINESS OWNER"
      },
      {
        "name": "GRAHAM, VALERIE",
        "amount": 250.0,
        "date": "2025-08-17",
        "city": "DOWNSVILLE",
        "state": "LA",
        "employer": "SELF",
        "occupation": "ASSISTING MY HUSBAND WITH HIS BUSINESS"
      },
      {
        "name": "DYE, JOHN",
        "amount": 250.0,
        "date": "2025-08-10",
        "city": "CEDAR PARK",
        "state": "TX",
        "employer": "FORCE MULTIPLIER",
        "occupation": "MARKETER"
      },
      {
        "name": "ARMSTRONG, JOHNNY",
        "amount": 100.0,
        "date": "2025-08-10",
        "city": "RUSTON",
        "state": "LA",
        "employer": "NOT EMPLOYED",
        "occupation": "NOT EMPLOYED"
      },
      {
        "name": "VOSS, JACKSON",
        "amount": 250.0,
        "date": "2025-07-27",
        "city": "NEW ORLEANS",
        "state": "LA",
        "employer": "ALLIANCE FOR AFFORDABLE ENERGY",
        "occupation": "POLICY COORDINATOR"
      }
    ],
    "pac_contributions": []
  },
  {
    "candidate_name": "CACERES, GABRIEL",
    "candidate_id": "H6PA03161",
    "committee_id": null,
    "individual_contributions": [],
    "pac_contributions": []
  },
  {
    "candidate_name": "CADORE, ZOE",
    "candidate_id": "H6TX18331",
    "committee_id": null,
    "individual_contributions": [],
    "pac_contributions": []
  },
  {
    "candidate_name": "CAHILL, JASON",
    "candidate_id": "H6TX21350",
    "committee_id": "C00921247",
    "individual_contributions": [
      {
        "name": "LOHRINGEL, LAVERNE",
        "amount": 500.0,
        "date": "2025-09-30",
        "city": "LAKEWOOD",
        "state": "CO",
        "employer": "RETIRED",
        "occupation": "RETIRED"
      },
      {
        "name": "HAWORTH, BRIAN",
        "amount": 500.0,
        "date": "2025-09-30",
        "city": "BOERNE",
        "state": "TX",
        "employer": "SELF",
        "occupation": "PHYSICIAN"
      },
      {
        "name": "GARCIA, CARLOS",
        "amount": 500.0,
        "date": "2025-09-30",
        "city": "SAN ANTONIO",
        "state": "TX",
        "employer": "EL CHAPARRAL MEXICAN RESTAURANT",
        "occupation": "SELF EMPLOYED"
      },
      {
        "name": "CAHILL, FLORENCE",
        "amount": 3500.0,
        "date": "2025-09-30",
        "city": "SAN ANTONIO",
        "state": "TX",
        "employer": "RETIRED",
        "occupation": "RETIRED"
      },
      {
        "name": "CAHILL, FLORENCE",
        "amount": 3500.0,
        "date": "2025-09-30",
        "city": "SAN ANTONIO",
        "state": "TX",
        "employer": "RETIRED",
        "occupation": "RETIRED"
      },
      {
        "name": "CAHILL, FLORENCE",
        "amount": 3500.0,
        "date": "2025-09-30",
        "city": "SAN ANTONIO",
        "state": "TX",
        "employer": "RETIRED",
        "occupation": "RETIRED"
      },
      {
        "name": "OLLEROS, RAFAEL",
        "amount": 500.0,
        "date": "2025-09-29",
        "city": "MCALLEN",
        "state": "TX",
        "employer": "IBM",
        "occupation": "EXECUTIVE CONSULTANT"
      },
      {
        "name": "GORMAN, ARI",
        "amount": 1000.0,
        "date": "2025-09-29",
        "city": "SAN ANTONIO",
        "state": "TX",
        "employer": "GO2UNO",
        "occupation": "TELECOM ENG."
      },
      {
        "name": "GLANDER, TROY",
        "amount": 3500.0,
        "date": "2025-09-29",
        "city": "SAN ANTONIO",
        "state": "TX",
        "employer": "NAVA & GLANDER, PLLC",
        "occupation": "ATTORNEY"
      },
      {
        "name": "FRANSON, GLENN",
        "amount": 1000.0,
        "date": "2025-09-29",
        "city": "SAN ANTONIO",
        "state": "TX",
        "employer": "ELEVATED BRANDS",
        "occupation": "BUSINESS OWNER"
      },
      {
        "name": "EVANS, SHANE",
        "amount": 250.0,
        "date": "2025-09-29",
        "city": "SAN ANTONIO",
        "state": "TX",
        "employer": "ELEVATED BRANDS FRANCHISING",
        "occupation": "CEO"
      },
      {
        "name": "ESCOBEDO, VICTOR",
        "amount": 3500.0,
        "date": "2025-09-29",
        "city": "SPRING BRANCH",
        "state": "TX",
        "employer": "FALCON GENERAL CONTRACTORS",
        "occupation": "CONTRACTING"
      },
      {
        "name": "CAHILL, DENNIS",
        "amount": 3500.0,
        "date": "2025-09-29",
        "city": "BOERNE",
        "state": "TX",
        "employer": "RETIRED",
        "occupation": "RETIRED"
      },
      {
        "name": "CAHILL, DENNIS",
        "amount": 3500.0,
        "date": "2025-09-29",
        "city": "BOERNE",
        "state": "TX",
        "employer": "RETIRED",
        "occupation": "RETIRED"
      },
      {
        "name": "CAHILL, DENNIS",
        "amount": 3500.0,
        "date": "2025-09-29",
        "city": "BOERNE",
        "state": "TX",
        "employer": "RETIRED",
        "occupation": "RETIRED"
      },
      {
        "name": "ALI, JUNAB",
        "amount": 500.0,
        "date": "2025-09-29",
        "city": "AUSTIN",
        "state": "TX",
        "employer": "RETIRED",
        "occupation": "RETIRED"
      }
    ],
    "pac_contributions": [
      {
        "name": "CAHILL, JASON",
        "amount": 250000.0,
        "date": "2025-09-29",
        "city": "BOERNE",
        "state": "TX",
        "employer": "SELF",
        "occupation": "CANDIDATE",
        "committee_id": "C00921247"
      }
    ]
  },
  {
    "candidate_name": "CAIN, BRISCOE ROWELL III",
    "candidate_id": "H6TX09124",
    "committee_id": "C00917393",
    "individual_contributions": [
      {
        "name": "WALKER, LEE",
        "amount": 250.0,
        "date": "2025-09-30",
        "city": "SPLENDORA",
        "state": "TX",
        "employer": "SELF",
        "occupation": "REAL ESTATE DEVELOPER"
      },
      {
        "name": "VICK, GILES",
        "amount": 250.0,
        "date": "2025-09-30",
        "city": "HOUSTON",
        "state": "TX",
        "employer": "BAYLOR COLLEGE OF MEDICINE",
        "occupation": "PHYSICIAN"
      },
      {
        "name": "STRAHAN, ADAM",
        "amount": 500.0,
        "date": "2025-09-30",
        "city": "RICHMOND",
        "state": "TX",
        "employer": "STRAHAN LAW FIRM, PLLC",
        "occupation": "ATTORNEY"
      },
      {
        "name": "SIMPSON, DAVID",
        "amount": 250.0,
        "date": "2025-09-30",
        "city": "AVINGER",
        "state": "TX",
        "employer": "SELF-EMPLOYED",
        "occupation": "TIMBERLAND STEWARD"
      },
      {
        "name": "SCHNAUTZ, DANNY",
        "amount": 750.0,
        "date": "2025-09-30",
        "city": "PASADENA",
        "state": "TX",
        "employer": "CLARK",
        "occupation": "MANAGER"
      },
      {
        "name": "POLK, PRESTON",
        "amount": 500.0,
        "date": "2025-09-30",
        "city": "FORT WORTH",
        "state": "TX",
        "employer": "LAW FIRM",
        "occupation": "ATTORNEY"
      },
      {
        "name": "POLK, ANDREW",
        "amount": 500.0,
        "date": "2025-09-30",
        "city": "LUFKIN",
        "state": "TX",
        "employer": "ANGELINA SAVINGS BANK",
        "occupation": "SR. VP"
      },
      {
        "name": "OWEN, CHARLOTTE",
        "amount": 1000.0,
        "date": "2025-09-30",
        "city": "SEGUIN",
        "state": "TX",
        "employer": "SELF",
        "occupation": "FDA REGULATION CONSULTANT"
      },
      {
        "name": "OGDEN, WILLIAM",
        "amount": 2500.0,
        "date": "2025-09-30",
        "city": "HOUSTON",
        "state": "TX",
        "employer": "KASTER LYNCH FARRAR  BALL LLP",
        "occupation": "LAWYER"
      },
      {
        "name": "OBERHOFF, DONICA",
        "amount": 2500.0,
        "date": "2025-09-30",
        "city": "SAN ANTONIO",
        "state": "TX",
        "employer": "DIRECTOR OF GOVT",
        "occupation": "ACADIAN AMBULANCE SERVICE"
      },
      {
        "name": "MORGAN, MARY",
        "amount": 500.0,
        "date": "2025-09-30",
        "city": "CROSBY",
        "state": "TX",
        "employer": "RETIRED",
        "occupation": "RETIRED"
      },
      {
        "name": "MCCORMICK, MCCRAE",
        "amount": 500.0,
        "date": "2025-09-30",
        "city": "FLOYDADA",
        "state": "TX",
        "employer": "SELF",
        "occupation": "FARMER AND RANCHER"
      },
      {
        "name": "HAYES, RICHARD",
        "amount": 2500.0,
        "date": "2025-09-30",
        "city": "DENTON",
        "state": "TX",
        "employer": "HAYES, BERRY, WHITE VANZANT, LLP",
        "occupation": "LAWYER"
      },
      {
        "name": "GLAZE, JOHN",
        "amount": 250.0,
        "date": "2025-09-30",
        "city": "HOUSTON",
        "state": "TX",
        "employer": "FAST TRACK SPECIALTIES, LP",
        "occupation": "JOB MAKER"
      },
      {
        "name": "GIBSON, GARRETT",
        "amount": 500.0,
        "date": "2025-09-30",
        "city": "HOUSTON",
        "state": "TX",
        "employer": "JONES DAY",
        "occupation": "LAWYER"
      },
      {
        "name": "DYER, DON",
        "amount": 3500.0,
        "date": "2025-09-30",
        "city": "AUSTIN",
        "state": "TX",
        "employer": "P.J.S.OF TEXAS INC.",
        "occupation": "CEO"
      },
      {
        "name": "DYER, DON",
        "amount": 3500.0,
        "date": "2025-09-30",
        "city": "AUSTIN",
        "state": "TX",
        "employer": "P.J.S.OF TEXAS INC.",
        "occupation": "CEO"
      },
      {
        "name": "DORAZIO, MARK",
        "amount": 1000.0,
        "date": "2025-09-30",
        "city": "SAN ANTONIO",
        "state": "TX",
        "employer": "DORAZIO ENTERPRISES",
        "occupation": "OWNER"
      },
      {
        "name": "CUNNINGHAM, CHARLES",
        "amount": 1000.0,
        "date": "2025-09-30",
        "city": "HUMBLE",
        "state": "TX",
        "employer": "STATE OF TX",
        "occupation": "REPRESENTATIVE"
      },
      {
        "name": "CREAGER, ADOLPH",
        "amount": 1000.0,
        "date": "2025-09-30",
        "city": "DEER PARK",
        "state": "TX",
        "employer": "RETIRED",
        "occupation": "RETIRED"
      },
      {
        "name": "COOK, DAVID",
        "amount": 1000.0,
        "date": "2025-09-30",
        "city": "MANSFIELD",
        "state": "TX",
        "employer": "HARRIS COOK",
        "occupation": "ATTORNEY"
      },
      {
        "name": "CONE, MATTHEW",
        "amount": 1000.0,
        "date": "2025-09-30",
        "city": "HOUSTON",
        "state": "TX",
        "employer": "FRIO HOLDINGS LLC",
        "occupation": "OWNER"
      },
      {
        "name": "BURROWS, ELISABETH",
        "amount": 2000.0,
        "date": "2025-09-30",
        "city": "LUBBOCK",
        "state": "TX",
        "employer": "SELF",
        "occupation": "SELF"
      },
      {
        "name": "BRUENING, LOREN",
        "amount": 250.0,
        "date": "2025-09-30",
        "city": "CROSBY",
        "state": "TX",
        "employer": "SELF",
        "occupation": "TRANSPORTATION BROKER"
      },
      {
        "name": "BONNEN, KIM",
        "amount": 1000.0,
        "date": "2025-09-30",
        "city": "LAKE JACKSON",
        "state": "TX",
        "employer": "SECOND FLOOR STRATEGIES",
        "occupation": "CONSULTANT"
      },
      {
        "name": "ANDERSON, CARSON",
        "amount": 1500.0,
        "date": "2025-09-30",
        "city": "FLORENCE",
        "state": "AL",
        "employer": "FIRST SOUTHERN BANK",
        "occupation": "EXECUTIVE"
      },
      {
        "name": "AKHUND, ANIK",
        "amount": 1500.0,
        "date": "2025-09-30",
        "city": "AUSTIN",
        "state": "TX",
        "employer": "SELF",
        "occupation": "BUSINESS OWNER"
      },
      {
        "name": "AKHUND, ANIK",
        "amount": 3500.0,
        "date": "2025-09-30",
        "city": "AUSTIN",
        "state": "TX",
        "employer": "SELF",
        "occupation": "BUSINESS OWNER"
      },
      {
        "name": "YOKUBAITIS, RB",
        "amount": 3500.0,
        "date": "2025-09-29",
        "city": "AUSTIN",
        "state": "TX",
        "employer": "SELF EMPLOYED",
        "occupation": "OWNER"
      },
      {
        "name": "YOKUBAITIS, CM",
        "amount": 3500.0,
        "date": "2025-09-29",
        "city": "AUSTIN",
        "state": "TX",
        "employer": "SELF EMPLOYED",
        "occupation": "OWNER"
      },
      {
        "name": "RICHARDSON, KERESA",
        "amount": 1000.0,
        "date": "2025-09-29",
        "city": "MCKINNEY",
        "state": "TX",
        "employer": "TEXAS HOUSE OF REPRESENTATIVES",
        "occupation": "STATE REPRESENTATIVE"
      },
      {
        "name": "POSEY, JAKE",
        "amount": 1000.0,
        "date": "2025-09-29",
        "city": "GEORGETOWN",
        "state": "TX",
        "employer": "THE POSEY LAW FIRM",
        "occupation": "ATTORNEY"
      },
      {
        "name": "POLK, MARY GRACE",
        "amount": 500.0,
        "date": "2025-09-29",
        "city": "FORT WORTH",
        "state": "TX",
        "employer": "HIGGINBOTHAM",
        "occupation": "INSURANCE AGENT"
      },
      {
        "name": "POLK, CARL RAY JR",
        "amount": 2500.0,
        "date": "2025-09-29",
        "city": "LUFKIN",
        "state": "TX",
        "employer": "POLK LAND  CATTLE",
        "occupation": "RANCHER"
      },
      {
        "name": "OLCOTT, MICHAEL C",
        "amount": 2000.0,
        "date": "2025-09-29",
        "city": "FORT WORTH",
        "state": "TX",
        "employer": "RETIRED",
        "occupation": "RETIRED"
      },
      {
        "name": "LOEWY, PHILIPPA",
        "amount": 1500.0,
        "date": "2025-09-29",
        "city": "AUSTIN",
        "state": "TX",
        "employer": "LOEWY LAW FIRM",
        "occupation": "HR DIRECTOR"
      },
      {
        "name": "LOEWY, ADAM",
        "amount": 3500.0,
        "date": "2025-09-29",
        "city": "AUSTIN",
        "state": "TX",
        "employer": "LOEWY LAW FIRM",
        "occupation": "LAW"
      },
      {
        "name": "ISBELL, JJ",
        "amount": 2500.0,
        "date": "2025-09-29",
        "city": "PASADENA",
        "state": "TX",
        "employer": "TTE",
        "occupation": "PRESIDENT"
      },
      {
        "name": "HOFFMAN, JOY",
        "amount": 1000.0,
        "date": "2025-09-29",
        "city": "GREENWOOD VILLAGE",
        "state": "CO",
        "employer": "RETIRED",
        "occupation": "RETIRED"
      },
      {
        "name": "HARPER, JOHN",
        "amount": 250.0,
        "date": "2025-09-29",
        "city": "HEATH",
        "state": "TX",
        "employer": "RETIRED",
        "occupation": "RETIRED"
      },
      {
        "name": "FRANK, JAMES",
        "amount": 2500.0,
        "date": "2025-09-29",
        "city": "WICHITA FALLS",
        "state": "TX",
        "employer": "STATE OF TX",
        "occupation": "REPRESENTATIVE"
      },
      {
        "name": "BURKE, MARCELLA",
        "amount": 250.0,
        "date": "2025-09-29",
        "city": "HOUSTON",
        "state": "TX",
        "employer": "SELF",
        "occupation": "ATTORNEY"
      },
      {
        "name": "BIHM, BROCK",
        "amount": 500.0,
        "date": "2025-09-29",
        "city": "LA PORTE",
        "state": "TX",
        "employer": "MR. ELECTRIC OF BAY AREA",
        "occupation": "OWNER"
      },
      {
        "name": "WALL, HENRY",
        "amount": 250.0,
        "date": "2025-09-28",
        "city": "DEER PARK",
        "state": "TX",
        "employer": "MCCANN SERVICEDS",
        "occupation": "ENGINEER"
      },
      {
        "name": "HARRIS, AARON",
        "amount": 500.0,
        "date": "2025-09-28",
        "city": "NORTH RICHLAND HIL",
        "state": "TX",
        "employer": "LMK STRATEGIES",
        "occupation": "COFFEE MAKER"
      },
      {
        "name": "ADDISON, JOHN",
        "amount": 250.0,
        "date": "2025-09-28",
        "city": "LIBERTY",
        "state": "TX",
        "employer": "BAYWAY DODGE",
        "occupation": "GENERAL MANAGER"
      },
      {
        "name": "COPELAND, STEVE",
        "amount": 1000.0,
        "date": "2025-09-27",
        "city": "LA PORTE",
        "state": "TX",
        "employer": "RETIRED",
        "occupation": "RETIRED"
      },
      {
        "name": "MORLOT, BUCKLEY",
        "amount": 250.0,
        "date": "2025-09-26",
        "city": "HOUSTON",
        "state": "TX",
        "employer": "TEXANS FOR LAWSUIT REFORM",
        "occupation": "ADVANCEMENT"
      },
      {
        "name": "HULL, ASHLEE",
        "amount": 250.0,
        "date": "2025-09-26",
        "city": "HOUSTON",
        "state": "TX",
        "employer": "UNEMPLOYED",
        "occupation": "UNEMPLOYED"
      },
      {
        "name": "YBARRA, RUSSELL",
        "amount": 2000.0,
        "date": "2025-09-25",
        "city": "HOUSTON",
        "state": "TX",
        "employer": "GRINGOS TEX MEX",
        "occupation": "FOOD SERVICE"
      },
      {
        "name": "WALKER, LEE",
        "amount": 250.0,
        "date": "2025-09-30",
        "city": "SPLENDORA",
        "state": "TX",
        "employer": "SELF",
        "occupation": "REAL ESTATE DEVELOPER"
      },
      {
        "name": "VICK, GILES",
        "amount": 250.0,
        "date": "2025-09-30",
        "city": "HOUSTON",
        "state": "TX",
        "employer": "BAYLOR COLLEGE OF MEDICINE",
        "occupation": "PHYSICIAN"
      },
      {
        "name": "STRAHAN, ADAM",
        "amount": 500.0,
        "date": "2025-09-30",
        "city": "RICHMOND",
        "state": "TX",
        "employer": "STRAHAN LAW FIRM, PLLC",
        "occupation": "ATTORNEY"
      },
      {
        "name": "SIMPSON, DAVID",
        "amount": 250.0,
        "date": "2025-09-30",
        "city": "AVINGER",
        "state": "TX",
        "employer": "SELF-EMPLOYED",
        "occupation": "TIMBERLAND STEWARD"
      },
      {
        "name": "SCHNAUTZ, DANNY",
        "amount": 750.0,
        "date": "2025-09-30",
        "city": "PASADENA",
        "state": "TX",
        "employer": "CLARK",
        "occupation": "MANAGER"
      },
      {
        "name": "POLK, PRESTON",
        "amount": 500.0,
        "date": "2025-09-30",
        "city": "FORT WORTH",
        "state": "TX",
        "employer": "LAW FIRM",
        "occupation": "ATTORNEY"
      },
      {
        "name": "POLK, ANDREW",
        "amount": 500.0,
        "date": "2025-09-30",
        "city": "LUFKIN",
        "state": "TX",
        "employer": "ANGELINA SAVINGS BANK",
        "occupation": "SR. VP"
      },
      {
        "name": "OWEN, CHARLOTTE",
        "amount": 1000.0,
        "date": "2025-09-30",
        "city": "SEGUIN",
        "state": "TX",
        "employer": "SELF",
        "occupation": "FDA REGULATION CONSULTANT"
      },
      {
        "name": "OGDEN, WILLIAM",
        "amount": 2500.0,
        "date": "2025-09-30",
        "city": "HOUSTON",
        "state": "TX",
        "employer": "KASTER LYNCH FARRAR  BALL LLP",
        "occupation": "LAWYER"
      },
      {
        "name": "OBERHOFF, DONICA",
        "amount": 2500.0,
        "date": "2025-09-30",
        "city": "SAN ANTONIO",
        "state": "TX",
        "employer": "DIRECTOR OF GOVT",
        "occupation": "ACADIAN AMBULANCE SERVICE"
      },
      {
        "name": "MORGAN, MARY",
        "amount": 500.0,
        "date": "2025-09-30",
        "city": "CROSBY",
        "state": "TX",
        "employer": "RETIRED",
        "occupation": "RETIRED"
      },
      {
        "name": "MCCORMICK, MCCRAE",
        "amount": 500.0,
        "date": "2025-09-30",
        "city": "FLOYDADA",
        "state": "TX",
        "employer": "SELF",
        "occupation": "FARMER AND RANCHER"
      },
      {
        "name": "HAYES, RICHARD",
        "amount": 2500.0,
        "date": "2025-09-30",
        "city": "DENTON",
        "state": "TX",
        "employer": "HAYES, BERRY, WHITE VANZANT, LLP",
        "occupation": "LAWYER"
      },
      {
        "name": "GLAZE, JOHN",
        "amount": 250.0,
        "date": "2025-09-30",
        "city": "HOUSTON",
        "state": "TX",
        "employer": "FAST TRACK SPECIALTIES, LP",
        "occupation": "JOB MAKER"
      },
      {
        "name": "GIBSON, GARRETT",
        "amount": 500.0,
        "date": "2025-09-30",
        "city": "HOUSTON",
        "state": "TX",
        "employer": "JONES DAY",
        "occupation": "LAWYER"
      },
      {
        "name": "DYER, DON",
        "amount": 3500.0,
        "date": "2025-09-30",
        "city": "AUSTIN",
        "state": "TX",
        "employer": "P.J.S.OF TEXAS INC.",
        "occupation": "CEO"
      },
      {
        "name": "DYER, DON",
        "amount": 3500.0,
        "date": "2025-09-30",
        "city": "AUSTIN",
        "state": "TX",
        "employer": "P.J.S.OF TEXAS INC.",
        "occupation": "CEO"
      },
      {
        "name": "DORAZIO, MARK",
        "amount": 1000.0,
        "date": "2025-09-30",
        "city": "SAN ANTONIO",
        "state": "TX",
        "employer": "DORAZIO ENTERPRISES",
        "occupation": "OWNER"
      },
      {
        "name": "CUNNINGHAM, CHARLES",
        "amount": 1000.0,
        "date": "2025-09-30",
        "city": "HUMBLE",
        "state": "TX",
        "employer": "STATE OF TX",
        "occupation": "REPRESENTATIVE"
      },
      {
        "name": "CREAGER, ADOLPH",
        "amount": 1000.0,
        "date": "2025-09-30",
        "city": "DEER PARK",
        "state": "TX",
        "employer": "RETIRED",
        "occupation": "RETIRED"
      },
      {
        "name": "COOK, DAVID",
        "amount": 1000.0,
        "date": "2025-09-30",
        "city": "MANSFIELD",
        "state": "TX",
        "employer": "HARRIS COOK",
        "occupation": "ATTORNEY"
      },
      {
        "name": "CONE, MATTHEW",
        "amount": 1000.0,
        "date": "2025-09-30",
        "city": "HOUSTON",
        "state": "TX",
        "employer": "FRIO HOLDINGS LLC",
        "occupation": "OWNER"
      },
      {
        "name": "BURROWS, ELISABETH",
        "amount": 2000.0,
        "date": "2025-09-30",
        "city": "LUBBOCK",
        "state": "TX",
        "employer": "SELF",
        "occupation": "SELF"
      },
      {
        "name": "BRUENING, LOREN",
        "amount": 250.0,
        "date": "2025-09-30",
        "city": "CROSBY",
        "state": "TX",
        "employer": "SELF",
        "occupation": "TRANSPORTATION BROKER"
      },
      {
        "name": "BONNEN, KIM",
        "amount": 1000.0,
        "date": "2025-09-30",
        "city": "LAKE JACKSON",
        "state": "TX",
        "employer": "SECOND FLOOR STRATEGIES",
        "occupation": "CONSULTANT"
      },
      {
        "name": "ANDERSON, CARSON",
        "amount": 1500.0,
        "date": "2025-09-30",
        "city": "FLORENCE",
        "state": "AL",
        "employer": "FIRST SOUTHERN BANK",
        "occupation": "EXECUTIVE"
      },
      {
        "name": "AKHUND, ANIK",
        "amount": 1500.0,
        "date": "2025-09-30",
        "city": "AUSTIN",
        "state": "TX",
        "employer": "SELF",
        "occupation": "BUSINESS OWNER"
      },
      {
        "name": "AKHUND, ANIK",
        "amount": 3500.0,
        "date": "2025-09-30",
        "city": "AUSTIN",
        "state": "TX",
        "employer": "SELF",
        "occupation": "BUSINESS OWNER"
      },
      {
        "name": "YOKUBAITIS, RB",
        "amount": 3500.0,
        "date": "2025-09-29",
        "city": "AUSTIN",
        "state": "TX",
        "employer": "SELF EMPLOYED",
        "occupation": "OWNER"
      },
      {
        "name": "YOKUBAITIS, CM",
        "amount": 3500.0,
        "date": "2025-09-29",
        "city": "AUSTIN",
        "state": "TX",
        "employer": "SELF EMPLOYED",
        "occupation": "OWNER"
      },
      {
        "name": "RICHARDSON, KERESA",
        "amount": 1000.0,
        "date": "2025-09-29",
        "city": "MCKINNEY",
        "state": "TX",
        "employer": "TEXAS HOUSE OF REPRESENTATIVES",
        "occupation": "STATE REPRESENTATIVE"
      },
      {
        "name": "POSEY, JAKE",
        "amount": 1000.0,
        "date": "2025-09-29",
        "city": "GEORGETOWN",
        "state": "TX",
        "employer": "THE POSEY LAW FIRM",
        "occupation": "ATTORNEY"
      },
      {
        "name": "POLK, MARY GRACE",
        "amount": 500.0,
        "date": "2025-09-29",
        "city": "FORT WORTH",
        "state": "TX",
        "employer": "HIGGINBOTHAM",
        "occupation": "INSURANCE AGENT"
      },
      {
        "name": "POLK, CARL RAY JR",
        "amount": 2500.0,
        "date": "2025-09-29",
        "city": "LUFKIN",
        "state": "TX",
        "employer": "POLK LAND  CATTLE",
        "occupation": "RANCHER"
      },
      {
        "name": "OLCOTT, MICHAEL C",
        "amount": 2000.0,
        "date": "2025-09-29",
        "city": "FORT WORTH",
        "state": "TX",
        "employer": "RETIRED",
        "occupation": "RETIRED"
      },
      {
        "name": "LOEWY, PHILIPPA",
        "amount": 1500.0,
        "date": "2025-09-29",
        "city": "AUSTIN",
        "state": "TX",
        "employer": "LOEWY LAW FIRM",
        "occupation": "HR DIRECTOR"
      },
      {
        "name": "LOEWY, ADAM",
        "amount": 3500.0,
        "date": "2025-09-29",
        "city": "AUSTIN",
        "state": "TX",
        "employer": "LOEWY LAW FIRM",
        "occupation": "LAW"
      },
      {
        "name": "ISBELL, JJ",
        "amount": 2500.0,
        "date": "2025-09-29",
        "city": "PASADENA",
        "state": "TX",
        "employer": "TTE",
        "occupation": "PRESIDENT"
      },
      {
        "name": "HOFFMAN, JOY",
        "amount": 1000.0,
        "date": "2025-09-29",
        "city": "GREENWOOD VILLAGE",
        "state": "CO",
        "employer": "RETIRED",
        "occupation": "RETIRED"
      },
      {
        "name": "HARPER, JOHN",
        "amount": 250.0,
        "date": "2025-09-29",
        "city": "HEATH",
        "state": "TX",
        "employer": "RETIRED",
        "occupation": "RETIRED"
      },
      {
        "name": "FRANK, JAMES",
        "amount": 2500.0,
        "date": "2025-09-29",
        "city": "WICHITA FALLS",
        "state": "TX",
        "employer": "STATE OF TX",
        "occupation": "REPRESENTATIVE"
      },
      {
        "name": "BURKE, MARCELLA",
        "amount": 250.0,
        "date": "2025-09-29",
        "city": "HOUSTON",
        "state": "TX",
        "employer": "SELF",
        "occupation": "ATTORNEY"
      },
      {
        "name": "BIHM, BROCK",
        "amount": 500.0,
        "date": "2025-09-29",
        "city": "LA PORTE",
        "state": "TX",
        "employer": "MR. ELECTRIC OF BAY AREA",
        "occupation": "OWNER"
      },
      {
        "name": "WALL, HENRY",
        "amount": 250.0,
        "date": "2025-09-28",
        "city": "DEER PARK",
        "state": "TX",
        "employer": "MCCANN SERVICEDS",
        "occupation": "ENGINEER"
      },
      {
        "name": "HARRIS, AARON",
        "amount": 500.0,
        "date": "2025-09-28",
        "city": "NORTH RICHLAND HIL",
        "state": "TX",
        "employer": "LMK STRATEGIES",
        "occupation": "COFFEE MAKER"
      },
      {
        "name": "ADDISON, JOHN",
        "amount": 250.0,
        "date": "2025-09-28",
        "city": "LIBERTY",
        "state": "TX",
        "employer": "BAYWAY DODGE",
        "occupation": "GENERAL MANAGER"
      },
      {
        "name": "COPELAND, STEVE",
        "amount": 1000.0,
        "date": "2025-09-27",
        "city": "LA PORTE",
        "state": "TX",
        "employer": "RETIRED",
        "occupation": "RETIRED"
      },
      {
        "name": "MORLOT, BUCKLEY",
        "amount": 250.0,
        "date": "2025-09-26",
        "city": "HOUSTON",
        "state": "TX",
        "employer": "TEXANS FOR LAWSUIT REFORM",
        "occupation": "ADVANCEMENT"
      },
      {
        "name": "HULL, ASHLEE",
        "amount": 250.0,
        "date": "2025-09-26",
        "city": "HOUSTON",
        "state": "TX",
        "employer": "UNEMPLOYED",
        "occupation": "UNEMPLOYED"
      },
      {
        "name": "YBARRA, RUSSELL",
        "amount": 2000.0,
        "date": "2025-09-25",
        "city": "HOUSTON",
        "state": "TX",
        "employer": "GRINGOS TEX MEX",
        "occupation": "FOOD SERVICE"
      }
    ],
    "pac_contributions": [
      {
        "name": "CAIN, BRISCOE ROWELL III",
        "amount": 100000.0,
        "date": "2025-09-30",
        "city": "DEER PARK",
        "state": "TX",
        "employer": "SELF",
        "occupation": "CANDIDATE",
        "committee_id": "C00917393"
      },
      {
        "name": "GROWING OUR OWN DYNAMIC ECONOMY NOW",
        "amount": 5000.0,
        "date": "2025-09-30",
        "city": "TERRELL",
        "state": "TX",
        "employer": null,
        "occupation": null,
        "committee_id": "C00917393"
      },
      {
        "name": "BLESSEY MARINE SERVICE, INC. PAC",
        "amount": 1000.0,
        "date": "2025-09-30",
        "city": "HARAHAN",
        "state": "LA",
        "employer": null,
        "occupation": null,
        "committee_id": "C00917393"
      },
      {
        "name": "ACADIAN AMBULANCE  SERVICE EMPLOYEE FEDERAL PAC, INC.",
        "amount": 2500.0,
        "date": "2025-09-30",
        "city": "LAFAYETTE",
        "state": "LA",
        "employer": null,
        "occupation": null,
        "committee_id": "C00917393"
      },
      {
        "name": "WINRED",
        "amount": 250.0,
        "date": "2025-09-30",
        "city": "ARLINGTON",
        "state": "VA",
        "employer": null,
        "occupation": null,
        "committee_id": "C00917393"
      },
      {
        "name": "WINRED",
        "amount": 250.0,
        "date": "2025-09-30",
        "city": "ARLINGTON",
        "state": "VA",
        "employer": null,
        "occupation": null,
        "committee_id": "C00917393"
      },
      {
        "name": "TONY TINDERHOLT FOR TEXAS",
        "amount": 1000.0,
        "date": "2025-09-30",
        "city": "ARLINGTON",
        "state": "TX",
        "employer": null,
        "occupation": null,
        "committee_id": "C00917393"
      },
      {
        "name": "THOMAS4PASADENA",
        "amount": 1000.0,
        "date": "2025-09-30",
        "city": "PASADENA",
        "state": "TX",
        "employer": null,
        "occupation": null,
        "committee_id": "C00917393"
      },
      {
        "name": "WINRED",
        "amount": 500.0,
        "date": "2025-09-30",
        "city": "ARLINGTON",
        "state": "VA",
        "employer": null,
        "occupation": null,
        "committee_id": "C00917393"
      },
      {
        "name": "WINRED",
        "amount": 250.0,
        "date": "2025-09-30",
        "city": "ARLINGTON",
        "state": "VA",
        "employer": null,
        "occupation": null,
        "committee_id": "C00917393"
      },
      {
        "name": "WINRED",
        "amount": 750.0,
        "date": "2025-09-30",
        "city": "ARLINGTON",
        "state": "VA",
        "employer": null,
        "occupation": null,
        "committee_id": "C00917393"
      },
      {
        "name": "WINRED",
        "amount": 500.0,
        "date": "2025-09-30",
        "city": "ARLINGTON",
        "state": "VA",
        "employer": null,
        "occupation": null,
        "committee_id": "C00917393"
      },
      {
        "name": "WINRED",
        "amount": 500.0,
        "date": "2025-09-30",
        "city": "ARLINGTON",
        "state": "VA",
        "employer": null,
        "occupation": null,
        "committee_id": "C00917393"
      },
      {
        "name": "WINRED",
        "amount": 2500.0,
        "date": "2025-09-30",
        "city": "ARLINGTON",
        "state": "VA",
        "employer": null,
        "occupation": null,
        "committee_id": "C00917393"
      },
      {
        "name": "NATE SCHATZLINE FOR TEXAS CAMPAIGN",
        "amount": 1000.0,
        "date": "2025-09-30",
        "city": "FORT WORTH",
        "state": "TX",
        "employer": null,
        "occupation": null,
        "committee_id": "C00917393"
      },
      {
        "name": "WINRED",
        "amount": 500.0,
        "date": "2025-09-30",
        "city": "ARLINGTON",
        "state": "VA",
        "employer": null,
        "occupation": null,
        "committee_id": "C00917393"
      },
      {
        "name": "WINRED",
        "amount": 500.0,
        "date": "2025-09-30",
        "city": "ARLINGTON",
        "state": "VA",
        "employer": null,
        "occupation": null,
        "committee_id": "C00917393"
      },
      {
        "name": "WINRED",
        "amount": 2500.0,
        "date": "2025-09-30",
        "city": "ARLINGTON",
        "state": "VA",
        "employer": null,
        "occupation": null,
        "committee_id": "C00917393"
      },
      {
        "name": "WINRED",
        "amount": 250.0,
        "date": "2025-09-30",
        "city": "ARLINGTON",
        "state": "VA",
        "employer": null,
        "occupation": null,
        "committee_id": "C00917393"
      },
      {
        "name": "WINRED",
        "amount": 500.0,
        "date": "2025-09-30",
        "city": "ARLINGTON",
        "state": "VA",
        "employer": null,
        "occupation": null,
        "committee_id": "C00917393"
      },
      {
        "name": "FRIENDS OF TOM OLIVERSON",
        "amount": 1000.0,
        "date": "2025-09-30",
        "city": "HOUSTON",
        "state": "TX",
        "employer": null,
        "occupation": null,
        "committee_id": "C00917393"
      },
      {
        "name": "WINRED",
        "amount": 1000.0,
        "date": "2025-09-30",
        "city": "ARLINGTON",
        "state": "VA",
        "employer": null,
        "occupation": null,
        "committee_id": "C00917393"
      },
      {
        "name": "WINRED",
        "amount": 1000.0,
        "date": "2025-09-30",
        "city": "ARLINGTON",
        "state": "VA",
        "employer": null,
        "occupation": null,
        "committee_id": "C00917393"
      },
      {
        "name": "WINRED",
        "amount": 1000.0,
        "date": "2025-09-30",
        "city": "ARLINGTON",
        "state": "VA",
        "employer": null,
        "occupation": null,
        "committee_id": "C00917393"
      },
      {
        "name": "WINRED",
        "amount": 2000.0,
        "date": "2025-09-30",
        "city": "ARLINGTON",
        "state": "VA",
        "employer": null,
        "occupation": null,
        "committee_id": "C00917393"
      },
      {
        "name": "WINRED",
        "amount": 250.0,
        "date": "2025-09-30",
        "city": "ARLINGTON",
        "state": "VA",
        "employer": null,
        "occupation": null,
        "committee_id": "C00917393"
      },
      {
        "name": "WINRED",
        "amount": 1000.0,
        "date": "2025-09-30",
        "city": "ARLINGTON",
        "state": "VA",
        "employer": null,
        "occupation": null,
        "committee_id": "C00917393"
      },
      {
        "name": "VICTORY AND NATION PAC",
        "amount": 3500.0,
        "date": "2025-09-29",
        "city": "PLANO",
        "state": "TX",
        "employer": null,
        "occupation": null,
        "committee_id": "C00917393"
      },
      {
        "name": "WINRED",
        "amount": 1000.0,
        "date": "2025-09-29",
        "city": "ARLINGTON",
        "state": "VA",
        "employer": null,
        "occupation": null,
        "committee_id": "C00917393"
      },
      {
        "name": "WINRED",
        "amount": 1000.0,
        "date": "2025-09-29",
        "city": "ARLINGTON",
        "state": "VA",
        "employer": null,
        "occupation": null,
        "committee_id": "C00917393"
      },
      {
        "name": "WINRED",
        "amount": 500.0,
        "date": "2025-09-29",
        "city": "ARLINGTON",
        "state": "VA",
        "employer": null,
        "occupation": null,
        "committee_id": "C00917393"
      },
      {
        "name": "WINRED",
        "amount": 2500.0,
        "date": "2025-09-29",
        "city": "ARLINGTON",
        "state": "VA",
        "employer": null,
        "occupation": null,
        "committee_id": "C00917393"
      },
      {
        "name": "WINRED",
        "amount": 1500.0,
        "date": "2025-09-29",
        "city": "ARLINGTON",
        "state": "VA",
        "employer": null,
        "occupation": null,
        "committee_id": "C00917393"
      },
      {
        "name": "WINRED",
        "amount": 3500.0,
        "date": "2025-09-29",
        "city": "ARLINGTON",
        "state": "VA",
        "employer": null,
        "occupation": null,
        "committee_id": "C00917393"
      },
      {
        "name": "WINRED",
        "amount": 2500.0,
        "date": "2025-09-29",
        "city": "ARLINGTON",
        "state": "VA",
        "employer": null,
        "occupation": null,
        "committee_id": "C00917393"
      },
      {
        "name": "WINRED",
        "amount": 250.0,
        "date": "2025-09-29",
        "city": "ARLINGTON",
        "state": "VA",
        "employer": null,
        "occupation": null,
        "committee_id": "C00917393"
      },
      {
        "name": "WINRED",
        "amount": 250.0,
        "date": "2025-09-29",
        "city": "ARLINGTON",
        "state": "VA",
        "employer": null,
        "occupation": null,
        "committee_id": "C00917393"
      },
      {
        "name": "WINRED",
        "amount": 500.0,
        "date": "2025-09-29",
        "city": "ARLINGTON",
        "state": "VA",
        "employer": null,
        "occupation": null,
        "committee_id": "C00917393"
      },
      {
        "name": "WINRED",
        "amount": 250.0,
        "date": "2025-09-28",
        "city": "ARLINGTON",
        "state": "VA",
        "employer": null,
        "occupation": null,
        "committee_id": "C00917393"
      },
      {
        "name": "PAT CURRY CAMPAIGN",
        "amount": 1000.0,
        "date": "2025-09-28",
        "city": "WACO",
        "state": "TX",
        "employer": null,
        "occupation": null,
        "committee_id": "C00917393"
      },
      {
        "name": "WINRED",
        "amount": 500.0,
        "date": "2025-09-28",
        "city": "ARLINGTON",
        "state": "VA",
        "employer": null,
        "occupation": null,
        "committee_id": "C00917393"
      },
      {
        "name": "WINRED",
        "amount": 250.0,
        "date": "2025-09-28",
        "city": "ARLINGTON",
        "state": "VA",
        "employer": null,
        "occupation": null,
        "committee_id": "C00917393"
      },
      {
        "name": "HOLT FOR TEXAS",
        "amount": 1000.0,
        "date": "2025-09-27",
        "city": "SILSBEE",
        "state": "TX",
        "employer": null,
        "occupation": null,
        "committee_id": "C00917393"
      },
      {
        "name": "WINRED",
        "amount": 1000.0,
        "date": "2025-09-27",
        "city": "ARLINGTON",
        "state": "VA",
        "employer": null,
        "occupation": null,
        "committee_id": "C00917393"
      },
      {
        "name": "WINRED",
        "amount": 250.0,
        "date": "2025-09-26",
        "city": "ARLINGTON",
        "state": "VA",
        "employer": null,
        "occupation": null,
        "committee_id": "C00917393"
      },
      {
        "name": "MIKE GARCIA FOR TEXAS GOP",
        "amount": 1000.0,
        "date": "2025-09-26",
        "city": "AUSTIN",
        "state": "TX",
        "employer": null,
        "occupation": null,
        "committee_id": "C00917393"
      },
      {
        "name": "MATT KRAUSE CAMPAIGN",
        "amount": 1000.0,
        "date": "2025-09-26",
        "city": "KELLER",
        "state": "TX",
        "employer": null,
        "occupation": null,
        "committee_id": "C00917393"
      },
      {
        "name": "WINRED",
        "amount": 250.0,
        "date": "2025-09-26",
        "city": "ARLINGTON",
        "state": "VA",
        "employer": null,
        "occupation": null,
        "committee_id": "C00917393"
      },
      {
        "name": "WINRED",
        "amount": 2000.0,
        "date": "2025-09-25",
        "city": "ARLINGTON",
        "state": "VA",
        "employer": null,
        "occupation": null,
        "committee_id": "C00917393"
      },
      {
        "name": "WINRED",
        "amount": 3000.0,
        "date": "2025-09-25",
        "city": "ARLINGTON",
        "state": "VA",
        "employer": null,
        "occupation": null,
        "committee_id": "C00917393"
      },
      {
        "name": "CAIN, BRISCOE ROWELL III",
        "amount": 100000.0,
        "date": "2025-09-30",
        "city": "DEER PARK",
        "state": "TX",
        "employer": "SELF",
        "occupation": "CANDIDATE",
        "committee_id": "C00917393"
      },
      {
        "name": "GROWING OUR OWN DYNAMIC ECONOMY NOW",
        "amount": 5000.0,
        "date": "2025-09-30",
        "city": "TERRELL",
        "state": "TX",
        "employer": null,
        "occupation": null,
        "committee_id": "C00917393"
      },
      {
        "name": "BLESSEY MARINE SERVICE, INC. PAC",
        "amount": 1000.0,
        "date": "2025-09-30",
        "city": "HARAHAN",
        "state": "LA",
        "employer": null,
        "occupation": null,
        "committee_id": "C00917393"
      },
      {
        "name": "ACADIAN AMBULANCE  SERVICE EMPLOYEE FEDERAL PAC, INC.",
        "amount": 2500.0,
        "date": "2025-09-30",
        "city": "LAFAYETTE",
        "state": "LA",
        "employer": null,
        "occupation": null,
        "committee_id": "C00917393"
      },
      {
        "name": "WINRED",
        "amount": 250.0,
        "date": "2025-09-30",
        "city": "ARLINGTON",
        "state": "VA",
        "employer": null,
        "occupation": null,
        "committee_id": "C00917393"
      },
      {
        "name": "WINRED",
        "amount": 250.0,
        "date": "2025-09-30",
        "city": "ARLINGTON",
        "state": "VA",
        "employer": null,
        "occupation": null,
        "committee_id": "C00917393"
      },
      {
        "name": "TONY TINDERHOLT FOR TEXAS",
        "amount": 1000.0,
        "date": "2025-09-30",
        "city": "ARLINGTON",
        "state": "TX",
        "employer": null,
        "occupation": null,
        "committee_id": "C00917393"
      },
      {
        "name": "THOMAS4PASADENA",
        "amount": 1000.0,
        "date": "2025-09-30",
        "city": "PASADENA",
        "state": "TX",
        "employer": null,
        "occupation": null,
        "committee_id": "C00917393"
      },
      {
        "name": "WINRED",
        "amount": 500.0,
        "date": "2025-09-30",
        "city": "ARLINGTON",
        "state": "VA",
        "employer": null,
        "occupation": null,
        "committee_id": "C00917393"
      },
      {
        "name": "WINRED",
        "amount": 250.0,
        "date": "2025-09-30",
        "city": "ARLINGTON",
        "state": "VA",
        "employer": null,
        "occupation": null,
        "committee_id": "C00917393"
      },
      {
        "name": "WINRED",
        "amount": 750.0,
        "date": "2025-09-30",
        "city": "ARLINGTON",
        "state": "VA",
        "employer": null,
        "occupation": null,
        "committee_id": "C00917393"
      },
      {
        "name": "WINRED",
        "amount": 500.0,
        "date": "2025-09-30",
        "city": "ARLINGTON",
        "state": "VA",
        "employer": null,
        "occupation": null,
        "committee_id": "C00917393"
      },
      {
        "name": "WINRED",
        "amount": 500.0,
        "date": "2025-09-30",
        "city": "ARLINGTON",
        "state": "VA",
        "employer": null,
        "occupation": null,
        "committee_id": "C00917393"
      },
      {
        "name": "WINRED",
        "amount": 2500.0,
        "date": "2025-09-30",
        "city": "ARLINGTON",
        "state": "VA",
        "employer": null,
        "occupation": null,
        "committee_id": "C00917393"
      },
      {
        "name": "NATE SCHATZLINE FOR TEXAS CAMPAIGN",
        "amount": 1000.0,
        "date": "2025-09-30",
        "city": "FORT WORTH",
        "state": "TX",
        "employer": null,
        "occupation": null,
        "committee_id": "C00917393"
      },
      {
        "name": "WINRED",
        "amount": 500.0,
        "date": "2025-09-30",
        "city": "ARLINGTON",
        "state": "VA",
        "employer": null,
        "occupation": null,
        "committee_id": "C00917393"
      },
      {
        "name": "WINRED",
        "amount": 500.0,
        "date": "2025-09-30",
        "city": "ARLINGTON",
        "state": "VA",
        "employer": null,
        "occupation": null,
        "committee_id": "C00917393"
      },
      {
        "name": "WINRED",
        "amount": 2500.0,
        "date": "2025-09-30",
        "city": "ARLINGTON",
        "state": "VA",
        "employer": null,
        "occupation": null,
        "committee_id": "C00917393"
      },
      {
        "name": "WINRED",
        "amount": 250.0,
        "date": "2025-09-30",
        "city": "ARLINGTON",
        "state": "VA",
        "employer": null,
        "occupation": null,
        "committee_id": "C00917393"
      },
      {
        "name": "WINRED",
        "amount": 500.0,
        "date": "2025-09-30",
        "city": "ARLINGTON",
        "state": "VA",
        "employer": null,
        "occupation": null,
        "committee_id": "C00917393"
      },
      {
        "name": "FRIENDS OF TOM OLIVERSON",
        "amount": 1000.0,
        "date": "2025-09-30",
        "city": "HOUSTON",
        "state": "TX",
        "employer": null,
        "occupation": null,
        "committee_id": "C00917393"
      },
      {
        "name": "WINRED",
        "amount": 1000.0,
        "date": "2025-09-30",
        "city": "ARLINGTON",
        "state": "VA",
        "employer": null,
        "occupation": null,
        "committee_id": "C00917393"
      },
      {
        "name": "WINRED",
        "amount": 1000.0,
        "date": "2025-09-30",
        "city": "ARLINGTON",
        "state": "VA",
        "employer": null,
        "occupation": null,
        "committee_id": "C00917393"
      },
      {
        "name": "WINRED",
        "amount": 1000.0,
        "date": "2025-09-30",
        "city": "ARLINGTON",
        "state": "VA",
        "employer": null,
        "occupation": null,
        "committee_id": "C00917393"
      },
      {
        "name": "WINRED",
        "amount": 2000.0,
        "date": "2025-09-30",
        "city": "ARLINGTON",
        "state": "VA",
        "employer": null,
        "occupation": null,
        "committee_id": "C00917393"
      },
      {
        "name": "WINRED",
        "amount": 250.0,
        "date": "2025-09-30",
        "city": "ARLINGTON",
        "state": "VA",
        "employer": null,
        "occupation": null,
        "committee_id": "C00917393"
      },
      {
        "name": "WINRED",
        "amount": 1000.0,
        "date": "2025-09-30",
        "city": "ARLINGTON",
        "state": "VA",
        "employer": null,
        "occupation": null,
        "committee_id": "C00917393"
      },
      {
        "name": "VICTORY AND NATION PAC",
        "amount": 3500.0,
        "date": "2025-09-29",
        "city": "PLANO",
        "state": "TX",
        "employer": null,
        "occupation": null,
        "committee_id": "C00917393"
      },
      {
        "name": "WINRED",
        "amount": 1000.0,
        "date": "2025-09-29",
        "city": "ARLINGTON",
        "state": "VA",
        "employer": null,
        "occupation": null,
        "committee_id": "C00917393"
      },
      {
        "name": "WINRED",
        "amount": 1000.0,
        "date": "2025-09-29",
        "city": "ARLINGTON",
        "state": "VA",
        "employer": null,
        "occupation": null,
        "committee_id": "C00917393"
      },
      {
        "name": "WINRED",
        "amount": 500.0,
        "date": "2025-09-29",
        "city": "ARLINGTON",
        "state": "VA",
        "employer": null,
        "occupation": null,
        "committee_id": "C00917393"
      },
      {
        "name": "WINRED",
        "amount": 2500.0,
        "date": "2025-09-29",
        "city": "ARLINGTON",
        "state": "VA",
        "employer": null,
        "occupation": null,
        "committee_id": "C00917393"
      },
      {
        "name": "WINRED",
        "amount": 1500.0,
        "date": "2025-09-29",
        "city": "ARLINGTON",
        "state": "VA",
        "employer": null,
        "occupation": null,
        "committee_id": "C00917393"
      },
      {
        "name": "WINRED",
        "amount": 3500.0,
        "date": "2025-09-29",
        "city": "ARLINGTON",
        "state": "VA",
        "employer": null,
        "occupation": null,
        "committee_id": "C00917393"
      },
      {
        "name": "WINRED",
        "amount": 2500.0,
        "date": "2025-09-29",
        "city": "ARLINGTON",
        "state": "VA",
        "employer": null,
        "occupation": null,
        "committee_id": "C00917393"
      },
      {
        "name": "WINRED",
        "amount": 250.0,
        "date": "2025-09-29",
        "city": "ARLINGTON",
        "state": "VA",
        "employer": null,
        "occupation": null,
        "committee_id": "C00917393"
      },
      {
        "name": "WINRED",
        "amount": 250.0,
        "date": "2025-09-29",
        "city": "ARLINGTON",
        "state": "VA",
        "employer": null,
        "occupation": null,
        "committee_id": "C00917393"
      },
      {
        "name": "WINRED",
        "amount": 500.0,
        "date": "2025-09-29",
        "city": "ARLINGTON",
        "state": "VA",
        "employer": null,
        "occupation": null,
        "committee_id": "C00917393"
      },
      {
        "name": "WINRED",
        "amount": 250.0,
        "date": "2025-09-28",
        "city": "ARLINGTON",
        "state": "VA",
        "employer": null,
        "occupation": null,
        "committee_id": "C00917393"
      },
      {
        "name": "PAT CURRY CAMPAIGN",
        "amount": 1000.0,
        "date": "2025-09-28",
        "city": "WACO",
        "state": "TX",
        "employer": null,
        "occupation": null,
        "committee_id": "C00917393"
      },
      {
        "name": "WINRED",
        "amount": 500.0,
        "date": "2025-09-28",
        "city": "ARLINGTON",
        "state": "VA",
        "employer": null,
        "occupation": null,
        "committee_id": "C00917393"
      },
      {
        "name": "WINRED",
        "amount": 250.0,
        "date": "2025-09-28",
        "city": "ARLINGTON",
        "state": "VA",
        "employer": null,
        "occupation": null,
        "committee_id": "C00917393"
      },
      {
        "name": "HOLT FOR TEXAS",
        "amount": 1000.0,
        "date": "2025-09-27",
        "city": "SILSBEE",
        "state": "TX",
        "employer": null,
        "occupation": null,
        "committee_id": "C00917393"
      },
      {
        "name": "WINRED",
        "amount": 1000.0,
        "date": "2025-09-27",
        "city": "ARLINGTON",
        "state": "VA",
        "employer": null,
        "occupation": null,
        "committee_id": "C00917393"
      },
      {
        "name": "WINRED",
        "amount": 250.0,
        "date": "2025-09-26",
        "city": "ARLINGTON",
        "state": "VA",
        "employer": null,
        "occupation": null,
        "committee_id": "C00917393"
      },
      {
        "name": "MIKE GARCIA FOR TEXAS GOP",
        "amount": 1000.0,
        "date": "2025-09-26",
        "city": "AUSTIN",
        "state": "TX",
        "employer": null,
        "occupation": null,
        "committee_id": "C00917393"
      },
      {
        "name": "MATT KRAUSE CAMPAIGN",
        "amount": 1000.0,
        "date": "2025-09-26",
        "city": "KELLER",
        "state": "TX",
        "employer": null,
        "occupation": null,
        "committee_id": "C00917393"
      },
      {
        "name": "WINRED",
        "amount": 250.0,
        "date": "2025-09-26",
        "city": "ARLINGTON",
        "state": "VA",
        "employer": null,
        "occupation": null,
        "committee_id": "C00917393"
      },
      {
        "name": "WINRED",
        "amount": 2000.0,
        "date": "2025-09-25",
        "city": "ARLINGTON",
        "state": "VA",
        "employer": null,
        "occupation": null,
        "committee_id": "C00917393"
      },
      {
        "name": "WINRED",
        "amount": 3000.0,
        "date": "2025-09-25",
        "city": "ARLINGTON",
        "state": "VA",
        "employer": null,
        "occupation": null,
        "committee_id": "C00917393"
      }
    ]
  },
  {
    "candidate_name": "CALDWELL, BRENT",
    "candidate_id": "H6NC14036",
    "committee_id": "C00914549",
    "individual_contributions": [],
    "pac_contributions": []
  },
  {
    "candidate_name": "CALLAHAN, MARK ALLEN",
    "candidate_id": "H8OR05198",
    "committee_id": "C00651562",
    "individual_contributions": [],
    "pac_contributions": []
  },
  {
    "candidate_name": "CALL, JASON",
    "candidate_id": "H0WA02189",
    "committee_id": "C00765180",
    "individual_contributions": [],
    "pac_contributions": []
  },
  {
    "candidate_name": "CALONE, DAVID L",
    "candidate_id": "H6NY01118",
    "committee_id": "C00577080",
    "individual_contributions": [],
    "pac_contributions": []
  },
  {
    "candidate_name": "DUNLAP, MATT",
    "candidate_id": "H6ME02171",
    "committee_id": "C00922377",
    "individual_contributions": [],
    "pac_contributions": []
  },
  {
    "candidate_name": "HANSON, CARTER",
    "candidate_id": "H6CO01281",
    "committee_id": "C00911693",
    "individual_contributions": [],
    "pac_contributions": []
  }
]